kml2gpx/__init__.py
kml2gpx/__main__.py
kml2gpx/beans.py
kml2gpx/kml.py
kml2gpx/main.py
kml2gpx/private_radar.py
kml2gpx-0.0.1.dist-info/LICENSE
kml2gpx-0.0.1.dist-info/METADATA
kml2gpx-0.0.1.dist-info/WHEEL
kml2gpx-0.0.1.dist-info/entry_points.txt
kml2gpx-0.0.1.dist-info/top_level.txt
kml2gpx-0.0.1.dist-info/RECORD
