Metadata-Version: 2.1
Name: kml2gpx
Version: 0.0.1
Summary: Converts KML or flights from Private Radar to GPX
Author-email: Thomas Calmant <thomas.calmant@gmail.com>
License: Apache License
Project-URL: Homepage, https://github.com/tcalmant/kml2gpx
Project-URL: Bug Tracker, https://github.com/tcalmant/kml2gpx/issues
Keywords: kml,gpx,private-radar
Classifier: Programming Language :: Python :: 3
Classifier: License :: OSI Approved :: Apache Software License
Classifier: Operating System :: OS Independent
Requires-Python: >=3.7
License-File: LICENSE
Requires-Dist: requests (>=2.26.0)
Requires-Dist: gpxpy (>=1.5.0)
Requires-Dist: lxml (>=4.6.3)
